randcoor.py
randcoor-0.3.0.dist-info/LICENSE.txt
randcoor-0.3.0.dist-info/METADATA
randcoor-0.3.0.dist-info/WHEEL
randcoor-0.3.0.dist-info/top_level.txt
randcoor-0.3.0.dist-info/RECORD
