Metadata-Version: 2.1
Name: randcoor
Version: 0.3.0
Summary: Generates random coordinates and much more
Home-page: https://pypi.org/project/randcoor
Author: FromHumansImportDevs
Author-email: randcoor@msgsafe.io
License: Public Domain
Keywords: random position coordinates
Platform: UNKNOWN
Classifier: Programming Language :: Python :: 3
Classifier: Development Status :: 4 - Beta
Classifier: License :: Public Domain
Classifier: Operating System :: OS Independent
License-File: LICENSE.txt
